Beans/AirdInfo.py
Beans/BlockIndex.py
Beans/CV.py
Beans/Compressor.py
Beans/DDAMs.py
Beans/DDAPasefMs.py
Beans/DataProcessing.py
Beans/Instrument.py
Beans/Layers.py
Beans/MobiInfo.py
Beans/ParentFile.py
Beans/Software.py
Beans/WindowRange.py
Beans/__init__.py
Beans/Common/Spectrum.py
Beans/Common/Xic.py
Beans/Common/__init__.py
Compressor/ByteTrans.py
Compressor/Delta.py
Compressor/IntCompressor.py
Compressor/IntegratedIntCompressor.py
Compressor/__init__.py
Compressor/ByteComp/BrotliWrapper.py
Compressor/ByteComp/SnappyWrapper.py
Compressor/ByteComp/ZlibWrapper.py
Compressor/ByteComp/ZstdWrapper.py
Compressor/ByteComp/__init__.py
Compressor/IntComp/BinPackingWrapper.py
Compressor/IntComp/EmptyWrapper.py
Compressor/IntComp/VarByteWrapper.py
Compressor/IntComp/__init__.py
Compressor/SortedIntComp/DeltaWrapper.py
Compressor/SortedIntComp/IntegratedBinPackingWrapper.py
Compressor/SortedIntComp/IntegratedVarByteWrapper.py
Compressor/SortedIntComp/__init__.py
Constants/Features.py
Constants/PSI.py
Constants/SuffixConst.py
Constants/SymbolConst.py
Constants/__init__.py
Enums/AirdType.py
Enums/ByteCompType.py
Enums/DataDim.py
Enums/IntCompType.py
Enums/MsLevel.py
Enums/SortedIntCompType.py
Enums/__init__.py
Parser/BaseParser.py
Parser/DDAParser.py
Parser/DIAParser.py
Parser/PRMParser.py
Parser/__init__.py
Utils/AirdScanUtil.py
Utils/DDAUtil.py
Utils/__init__.py
AirdSDK-0.0.2.dist-info/METADATA
AirdSDK-0.0.2.dist-info/WHEEL
AirdSDK-0.0.2.dist-info/top_level.txt
AirdSDK-0.0.2.dist-info/RECORD
