Metadata-Version: 2.1
Name: AirdSDK
Version: 0.0.2
Summary: Aird SDK for python. AirdPro version > 4.0.0, Not support for BP comp
Home-page: https://github.com/CSi-Studio/Aird-SDK/
Author: CSi-Studio
Author-email: csi@csibio.net
Maintainer: Miaoshan Lu
License: Mulan PSL v2
Keywords: AirdPro,Aird,AirdSDK,ComboComp
Platform: UNKNOWN
Requires-Python: >=3.6
Requires-Dist: pyfastpfor (>=1.3.6)
Requires-Dist: Brotli (>=1.0.9)
Requires-Dist: python-snappy (>=0.6.1)
Requires-Dist: zstandard (>=0.18.0)
